holger11/__init__.py
holger11/holger11.py
holger11-0.4.dist-info/LICENSE.txt
holger11-0.4.dist-info/METADATA
holger11-0.4.dist-info/WHEEL
holger11-0.4.dist-info/top_level.txt
holger11-0.4.dist-info/RECORD
