Metadata-Version: 2.1
Name: holger11
Version: 0.4
Summary: Example library for educational purposes
Author: Yaromir Gusev
Author-email: yaromirarhideus@gmail.com
License: MIT
Classifier: Programming Language :: Python :: 3
Classifier: License :: OSI Approved :: MIT License
Classifier: Operating System :: OS Independent
Requires-Python: >=3.6
License-File: LICENSE.txt
Requires-Dist: pyperclip
